{
  "sample_id": "outdoor_sky_058A1889_s0",
  "bucket": "outdoor_sky",
  "classes": {
    "clothing": {
      "frac": 0.0867,
      "pixels": 60652,
      "lab_affine": {
        "L_scale": 0.7551,
        "L_shift": 60.0,
        "a_scale": 1.4975,
        "a_shift": -1.023,
        "b_scale": 0.5001,
        "b_shift": 0.967
      },
      "chroma_proxy": {
        "_approx": true,
        "_note": "heuristic Lab->slider projection, not validated against real Chroma renderer",
        "tint": -0.05113501995746213,
        "temperature": 0.04835723066397375,
        "saturation": -0.0012248545291638768,
        "vibrance": -0.0007
      }
    },
    "floor": {
      "frac": 0.2418,
      "pixels": 169116,
      "lab_affine": {
        "L_scale": 0.334,
        "L_shift": -20.141,
        "a_scale": 0.6504,
        "a_shift": 12.162,
        "b_scale": 0.6258,
        "b_shift": -40.0
      },
      "chroma_proxy": {
        "_approx": true,
        "_note": "heuristic Lab->slider projection, not validated against real Chroma renderer",
        "tint": 0.6080886501400357,
        "temperature": -1.0,
        "saturation": -0.36190860963939986,
        "vibrance": -0.2171
      }
    },
    "neutral": {
      "frac": 0.2476,
      "pixels": 173177,
      "lab_affine": {
        "L_scale": 1.0092,
        "L_shift": 2.591,
        "a_scale": 1.188,
        "a_shift": -0.895,
        "b_scale": 1.0128,
        "b_shift": -7.232
      },
      "chroma_proxy": {
        "_approx": true,
        "_note": "heuristic Lab->slider projection, not validated against real Chroma renderer",
        "tint": -0.044768120092031516,
        "temperature": -0.36160722679294305,
        "saturation": 0.10042150588419485,
        "vibrance": 0.0603
      }
    },
    "sky": {
      "frac": 0.3804,
      "pixels": 266015,
      "lab_affine": {
        "L_scale": 1.6333,
        "L_shift": -60.0,
        "a_scale": 4.003,
        "a_shift": -23.312,
        "b_scale": 0.5128,
        "b_shift": -29.388
      },
      "chroma_proxy": {
        "_approx": true,
        "_note": "heuristic Lab->slider projection, not validated against real Chroma renderer",
        "tint": -1.0,
        "temperature": -1.0,
        "saturation": 1.0,
        "vibrance": 0.6
      }
    }
  }
}