{
  "sample_id": "outdoor_sky_058A1940_s0",
  "bucket": "outdoor_sky",
  "classes": {
    "floor": {
      "frac": 0.2097,
      "pixels": 146637,
      "lab_affine": {
        "L_scale": 0.5552,
        "L_shift": -27.462,
        "a_scale": 0.5538,
        "a_shift": 5.693,
        "b_scale": 0.9373,
        "b_shift": -31.848
      },
      "chroma_proxy": {
        "_approx": true,
        "_note": "heuristic Lab->slider projection, not validated against real Chroma renderer",
        "tint": 0.2846716224471486,
        "temperature": -1.0,
        "saturation": -0.2544306338937514,
        "vibrance": -0.1527
      }
    },
    "neutral": {
      "frac": 0.3882,
      "pixels": 271535,
      "lab_affine": {
        "L_scale": 1.1067,
        "L_shift": -4.331,
        "a_scale": 1.0681,
        "a_shift": -2.594,
        "b_scale": 1.1272,
        "b_shift": -3.255
      },
      "chroma_proxy": {
        "_approx": true,
        "_note": "heuristic Lab->slider projection, not validated against real Chroma renderer",
        "tint": -0.12971326749116904,
        "temperature": -0.16272889588073078,
        "saturation": 0.09768038157491432,
        "vibrance": 0.0586
      }
    },
    "sky": {
      "frac": 0.3363,
      "pixels": 235175,
      "lab_affine": {
        "L_scale": 1.111,
        "L_shift": -1.668,
        "a_scale": 1.0,
        "a_shift": -18.131,
        "b_scale": 1.8094,
        "b_shift": 5.844
      },
      "chroma_proxy": {
        "_approx": true,
        "_note": "heuristic Lab->slider projection, not validated against real Chroma renderer",
        "tint": -0.9065472096204757,
        "temperature": 0.2922117944622634,
        "saturation": 0.4047006162402551,
        "vibrance": 0.2428
      }
    }
  }
}